svg_clip/VERSION
svg_clip/__init__.py
svg_clip/exceptions.py
svg_clip/parsers.py
svg_clip/heroicons/outline/academic-cap.svg
svg_clip/heroicons/outline/adjustments-horizontal.svg
svg_clip/heroicons/outline/adjustments-vertical.svg
svg_clip/heroicons/outline/archive-box-arrow-down.svg
svg_clip/heroicons/outline/archive-box-x-mark.svg
svg_clip/heroicons/outline/archive-box.svg
svg_clip/heroicons/outline/arrow-down-circle.svg
svg_clip/heroicons/outline/arrow-down-left.svg
svg_clip/heroicons/outline/arrow-down-on-square-stack.svg
svg_clip/heroicons/outline/arrow-down-on-square.svg
svg_clip/heroicons/outline/arrow-down-right.svg
svg_clip/heroicons/outline/arrow-down-tray.svg
svg_clip/heroicons/outline/arrow-down.svg
svg_clip/heroicons/outline/arrow-left-circle.svg
svg_clip/heroicons/outline/arrow-left-on-rectangle.svg
svg_clip/heroicons/outline/arrow-left.svg
svg_clip/heroicons/outline/arrow-long-down.svg
svg_clip/heroicons/outline/arrow-long-left.svg
svg_clip/heroicons/outline/arrow-long-right.svg
svg_clip/heroicons/outline/arrow-long-up.svg
svg_clip/heroicons/outline/arrow-path-rounded-square.svg
svg_clip/heroicons/outline/arrow-path.svg
svg_clip/heroicons/outline/arrow-right-circle.svg
svg_clip/heroicons/outline/arrow-right-on-rectangle.svg
svg_clip/heroicons/outline/arrow-right.svg
svg_clip/heroicons/outline/arrow-small-down.svg
svg_clip/heroicons/outline/arrow-small-left.svg
svg_clip/heroicons/outline/arrow-small-right.svg
svg_clip/heroicons/outline/arrow-small-up.svg
svg_clip/heroicons/outline/arrow-top-right-on-square.svg
svg_clip/heroicons/outline/arrow-trending-down.svg
svg_clip/heroicons/outline/arrow-trending-up.svg
svg_clip/heroicons/outline/arrow-up-circle.svg
svg_clip/heroicons/outline/arrow-up-left.svg
svg_clip/heroicons/outline/arrow-up-on-square-stack.svg
svg_clip/heroicons/outline/arrow-up-on-square.svg
svg_clip/heroicons/outline/arrow-up-right.svg
svg_clip/heroicons/outline/arrow-up-tray.svg
svg_clip/heroicons/outline/arrow-up.svg
django_svg_clip-1.0.2.dist-info/LICENSE.django
django_svg_clip-1.0.2.dist-info/LICENSE.md
django_svg_clip-1.0.2.dist-info/LICENSE.python
django_svg_clip-1.0.2.dist-info/METADATA
django_svg_clip-1.0.2.dist-info/WHEEL
django_svg_clip-1.0.2.dist-info/top_level.txt
django_svg_clip-1.0.2.dist-info/RECORD
