Metadata-Version: 2.1
Name: django-svg-clip
Version: 1.0.2
Summary: A simple django templatetag plugin for rendering and manipulating SVGs
Home-page: https://github.com/thisisdayal/svg-clip/
Author: Dayal Moirangthem
Author-email: thisisdayal7@gmail.com
License: MIT
Classifier: Framework :: Django
Classifier: Intended Audience :: Developers
Classifier: License :: OSI Approved :: MIT License
Classifier: Operating System :: OS Independent
Classifier: Programming Language :: Python
Classifier: Programming Language :: Python :: 3
Classifier: Programming Language :: Python :: 3 :: Only
Classifier: Programming Language :: Python :: 3.8
Classifier: Programming Language :: Python :: 3.9
Classifier: Programming Language :: Python :: 3.10
Requires-Python: >=3.8
License-File: LICENSE.django
License-File: LICENSE.md
License-File: LICENSE.python
Requires-Dist: django (<5,>=3.0)
Provides-Extra: test
Requires-Dist: black ; extra == 'test'
Requires-Dist: codecov ; extra == 'test'
Requires-Dist: coverage ; extra == 'test'
Requires-Dist: django ; extra == 'test'
Requires-Dist: flake8 ; extra == 'test'
Requires-Dist: gitchangelog ; extra == 'test'
Requires-Dist: isort ; extra == 'test'
Requires-Dist: mypy ; extra == 'test'
Requires-Dist: pytest-cov ; extra == 'test'
Requires-Dist: pystache ; extra == 'test'
Requires-Dist: pytest ; extra == 'test'
Requires-Dist: tox ; extra == 'test'
